ivona_api/__init__.py
ivona_api/exceptions.py
ivona_api/ivona_api.py
ivona_api/test/test_ivona_api.py
ivona_api-0.3.0.dist-info/DESCRIPTION.rst
ivona_api-0.3.0.dist-info/METADATA
ivona_api-0.3.0.dist-info/RECORD
ivona_api-0.3.0.dist-info/WHEEL
ivona_api-0.3.0.dist-info/metadata.json
ivona_api-0.3.0.dist-info/top_level.txt
