Metadata-Version: 2.0
Name: ivona-api
Version: 0.3.0
Summary: Python library that helps you connect to Amazon's IVONA Speech Cloud from within your Python project.
Home-page: https://github.com/Pythonity/python-ivona-api
Author: Paweł Adamczak
Author-email: pawel.adamczak@sidnet.info
License: MIT License
Download-URL: https://github.com/Pythonity/python-ivona-api/releases/latest
Keywords: amazon ivona api text to speech
Platform: UNKNOWN
Classifier: Development Status :: 4 - Beta
Classifier: Intended Audience :: Developers
Classifier: License :: OSI Approved :: MIT License
Classifier: Operating System :: OS Independent
Classifier: Programming Language :: Python
Classifier: Programming Language :: Python :: 2
Classifier: Programming Language :: Python :: 2.7
Classifier: Programming Language :: Python :: 3
Classifier: Programming Language :: Python :: 3.4
Classifier: Programming Language :: Python :: 3.5
Classifier: Programming Language :: Python :: 3.6
Classifier: Topic :: Software Development :: Libraries :: Python Modules
Requires-Dist: requests (>=2.18.1)
Requires-Dist: requests-aws4auth (>=0.9)
Requires-Dist: six (>=1.10.0)
Provides-Extra: testing
Requires-Dist: pytest; extra == 'testing'
